ddscatcli/__init__.py
ddscatcli/ddscat_cli.py
ddscatcli-1.0.3.dist-info/licenses/LICENSE
ddscatcli-1.0.3.dist-info/METADATA
ddscatcli-1.0.3.dist-info/WHEEL
ddscatcli-1.0.3.dist-info/entry_points.txt
ddscatcli-1.0.3.dist-info/top_level.txt
ddscatcli-1.0.3.dist-info/RECORD
