Metadata-Version: 2.4
Name: ddscatcli
Version: 1.0.3
Summary: CLI utility to edit and run a ddscat.par file for DDSCAT
Author-email: Clément Argentin <argentin-clement@outlook.fr>
License-Expression: GPL-3.0
Project-URL: Homepage, https://pypi.org/project/ddscatcli/
Project-URL: Repository, https://github.com/Argencle/ddscatcli
Project-URL: Changelog, https://github.com/Argencle/ddscatcli/blob/main/CHANGELOG.md
Keywords: DDSCAT,DDA,light scattering,cli
Classifier: Programming Language :: Python :: 3
Classifier: Environment :: Console
Classifier: Intended Audience :: Science/Research
Classifier: Intended Audience :: Education
Classifier: Topic :: Scientific/Engineering :: Physics
Classifier: Operating System :: OS Independent
Classifier: Development Status :: 4 - Beta
Requires-Python: >=3.8
License-File: LICENSE
Dynamic: license-file
